README.md
setup.cfg
setup.py
config/__init__.py
config/asgi.py
config/settings.py
config/urls.py
config/wsgi.py
iprogrammer_payme.egg-info/PKG-INFO
iprogrammer_payme.egg-info/SOURCES.txt
iprogrammer_payme.egg-info/dependency_links.txt
iprogrammer_payme.egg-info/requires.txt
iprogrammer_payme.egg-info/top_level.txt
jscorp_payme/__init__.py
jscorp_payme/admin.py
jscorp_payme/apps.py
jscorp_payme/authentication.py
jscorp_payme/methods_subscribe_api.py
jscorp_payme/models.py
jscorp_payme/status.py
jscorp_payme/views.py
jscorp_payme/management/__init__.py
jscorp_payme/management/commands/__init__.py
jscorp_payme/management/commands/create_paycom_user.py
jscorp_payme/migrations/0001_initial.py
jscorp_payme/migrations/__init__.py
jscorp_payme/payme/__init__.py
jscorp_payme/serializers/__init__.py
jscorp_payme/serializers/payme_operation.py