Metadata-Version: 2.1
Name: iprogrammer_payme
Version: 1.0.0
Summary: IProgrammer Payme
Home-page: https://github.com/ExcelentProgrammer/iprogrammer_payme
Author: A'zamov Samandar
Author-email: azamov.samandar.programmer@gmail.com
Classifier: Programming Language :: Python :: 3
Classifier: License :: OSI Approved :: MIT License
Requires-Python: >=3.5
Requires-Dist: requests
Requires-Dist: django
Requires-Dist: djangorestframework
